{
  "count": 36,
  "uniques": 23,
  "clones": [
    {
      "timestamp": "2023-01-23T00:00:00Z",
      "count": 7,
      "uniques": 5
    },
    {
      "timestamp": "2023-01-24T00:00:00Z",
      "count": 5,
      "uniques": 3
    },
    {
      "timestamp": "2023-01-25T00:00:00Z",
      "count": 5,
      "uniques": 3
    },
    {
      "timestamp": "2023-01-26T00:00:00Z",
      "count": 6,
      "uniques": 3
    },
    {
      "timestamp": "2023-01-27T00:00:00Z",
      "count": 7,
      "uniques": 5
    },
    {
      "timestamp": "2023-01-28T00:00:00Z",
      "count": 3,
      "uniques": 2
    },
    {
      "timestamp": "2023-01-29T00:00:00Z",
      "count": 3,
      "uniques": 2
    }
  ]
}