[
  {
    "path": "/MuYunyun/create-react-doc",
    "title": "MuYunyun/create-react-doc:  Minimalistic React-powered static site generator.",
    "count": 25,
    "uniques": 21
  },
  {
    "path": "/MuYunyun/create-react-doc/commits/main",
    "title": "Commits 路 MuYunyun/create-react-doc",
    "count": 4,
    "uniques": 1
  },
  {
    "path": "/MuYunyun/create-react-doc/tree/main/packages/crd-seed",
    "title": "create-react-doc/packages/crd-seed at main 路 MuYunyun/create-react-doc",
    "count": 2,
    "uniques": 1
  },
  {
    "path": "/MuYunyun/create-react-doc/blob/6ed2b39ed24ebef4c5f4a06549a3633d587abe49/package.json",
    "title": "create-react-doc/package.json at 6ed2b39ed24ebef4c5f4a06549a3633d587abe49 路 M...",
    "count": 1,
    "uniques": 1
  },
  {
    "path": "/MuYunyun/create-react-doc/blob/main/config.yml",
    "title": "create-react-doc/config.yml at main 路 MuYunyun/create-react-doc",
    "count": 1,
    "uniques": 1
  },
  {
    "path": "/MuYunyun/create-react-doc/blob/main/docs/%E4%B9%A6%E5%86%99%E7%BB%84%E4%BB%B6.md",
    "title": "create-react-doc/涔缁浠.md at main 路 MuYunyun/create-react-doc",
    "count": 1,
    "uniques": 1
  },
  {
    "path": "/MuYunyun/create-react-doc/blob/main/README-en.md",
    "title": "create-react-doc/README-en.md at main 路 MuYunyun/create-react-doc",
    "count": 1,
    "uniques": 1
  },
  {
    "path": "/MuYunyun/create-react-doc/blob/main/README.md",
    "title": "create-react-doc/README.md at main 路 MuYunyun/create-react-doc 路 GitHub",
    "count": 1,
    "uniques": 1
  },
  {
    "path": "/MuYunyun/create-react-doc/commit/6ed2b39ed24ebef4c5f4a06549a3633d587abe49",
    "title": "feat: init create-react-doc 路 MuYunyun/create-react-doc@6ed2b39",
    "count": 1,
    "uniques": 1
  },
  {
    "path": "/MuYunyun/create-react-doc/commit/bec361dc2de20071f96caef7ac2e0fe84abd9533",
    "title": "Initial commit 路 MuYunyun/create-react-doc@bec361d",
    "count": 1,
    "uniques": 1
  }
]